RepoRecon/__init__.py
RepoRecon/main.py
reporecon-1.0.9.dist-info/LICENSE
reporecon-1.0.9.dist-info/METADATA
reporecon-1.0.9.dist-info/WHEEL
reporecon-1.0.9.dist-info/entry_points.txt
reporecon-1.0.9.dist-info/top_level.txt
reporecon-1.0.9.dist-info/RECORD
