Metadata-Version: 2.2
Name: RepoRecon
Version: 1.0.9
Summary: A CLI tool to search GitHub repositories and integrate Gitleaks for scanning.
Home-page: https://github.com/CilynxGroup/RepoRecon
Author: Bentalem Abate
Author-email: bentalem.a@cilynx.com
Classifier: Programming Language :: Python :: 3
Classifier: License :: OSI Approved :: MIT License
Classifier: Operating System :: POSIX :: Linux
Classifier: Operating System :: Microsoft :: Windows
Requires-Python: >=3.6
License-File: LICENSE
Requires-Dist: boto3>=1.28.0
Requires-Dist: requests>=2.31.0
Requires-Dist: pyfiglet>=0.8.post1
Requires-Dist: rich>=13.5.2
Requires-Dist: stripe>=5.12.1
Requires-Dist: azure-identity==1.19.0
Requires-Dist: azure-mgmt-resource==23.2.0
Requires-Dist: azure-keyvault-secrets==4.9.0
Dynamic: author
Dynamic: author-email
Dynamic: classifier
Dynamic: description
Dynamic: description-content-type
Dynamic: home-page
Dynamic: requires-dist
Dynamic: requires-python
Dynamic: summary
